solana_actions/__init__.py
solana_actions/action_identity.py
solana_actions/constants.py
solana_actions/create_post_response.py
solana_actions/encode_url.py
solana_actions/fetch_transaction.py
solana_actions/find_reference.py
solana_actions/parse_url.py
solana_actions/types.py
solana_actions-0.2.1.dist-info/LICENSE
solana_actions-0.2.1.dist-info/METADATA
solana_actions-0.2.1.dist-info/WHEEL
solana_actions-0.2.1.dist-info/RECORD
