Metadata-Version: 2.1
Name: solana-actions
Version: 0.2.1
Summary: Solana Actions library
License: MIT
Author: Fabian Schuh
Author-email: mail@xeroc.org
Requires-Python: >=3.10,<4.0
Classifier: License :: OSI Approved :: MIT License
Classifier: Programming Language :: Python :: 3
Classifier: Programming Language :: Python :: 3.10
Classifier: Programming Language :: Python :: 3.11
Classifier: Programming Language :: Python :: 3.12
Requires-Dist: base58 (>=2.1.1,<3.0.0)
Requires-Dist: pydantic (>=2.7.4,<3.0.0)
Requires-Dist: pynacl (>=1.5.0,<2.0.0)
Requires-Dist: requests (>=2.32.3,<3.0.0)
Requires-Dist: solana (>=0.34.2,<0.35.0)
Requires-Dist: solders (>=0.21.0,<0.22.0)
